powerline_xcodeversion/__init__.py
powerline_xcodeversion/segments.py
powerline_xcodeversion-1.0.0.dist-info/LICENSE.md
powerline_xcodeversion-1.0.0.dist-info/METADATA
powerline_xcodeversion-1.0.0.dist-info/WHEEL
powerline_xcodeversion-1.0.0.dist-info/top_level.txt
powerline_xcodeversion-1.0.0.dist-info/RECORD
