Metadata-Version: 2.1
Name: powerline-xcodeversion
Version: 1.0.0
Summary: A Powerline segment for showing the active version of Xcode
Home-page: https://github.com/phatblat/powerline-xcodeversion
Author: Ben Chatelain
Author-email: ben@octop.ad
License: MIT
Keywords: powerline status prompt xcode version
Platform: UNKNOWN
Classifier: Programming Language :: Python :: 3
Classifier: License :: OSI Approved :: MIT License
Classifier: Operating System :: MacOS
Classifier: Environment :: Console
Classifier: Intended Audience :: Developers
Classifier: Topic :: Terminals
